doi_lookup/__init__.py
doi_lookup/doi.py
doi_lookup-0.0.1.dist-info/LICENSE
doi_lookup-0.0.1.dist-info/METADATA
doi_lookup-0.0.1.dist-info/WHEEL
doi_lookup-0.0.1.dist-info/top_level.txt
doi_lookup-0.0.1.dist-info/RECORD
