Metadata-Version: 2.1
Name: doi-lookup
Version: 0.0.1
Summary: A simple package to lookup information via DOI
Home-page: UNKNOWN
Author: Tahir Murata
Author-email: <tahirmurata83@gmail.com>
License: UNKNOWN
Keywords: python,doi,sci-hub,scihub,science,article,paper
Platform: UNKNOWN
Classifier: Development Status :: 3 - Alpha
Classifier: Intended Audience :: Education
Classifier: Programming Language :: Python :: 2
Classifier: Programming Language :: Python :: 3
Classifier: Operating System :: MacOS :: MacOS X
Classifier: Operating System :: Microsoft :: Windows
Requires-Dist: requests
